README.rst
setup.py
django_mindscape/__init__.py
django_mindscape/testing.py
django_mindscape.egg-info/PKG-INFO
django_mindscape.egg-info/SOURCES.txt
django_mindscape.egg-info/dependency_links.txt
django_mindscape.egg-info/entry_points.txt
django_mindscape.egg-info/not-zip-safe
django_mindscape.egg-info/requires.txt
django_mindscape.egg-info/top_level.txt
django_mindscape/tests/__init__.py
django_mindscape/tests/models.py
django_mindscape/tests/test_bidirectional.py
django_mindscape/tests/test_collect.py
django_mindscape/tests/test_dependencies.py
django_mindscape/tests/test_it.py