Metadata-Version: 1.1
Name: django-mindscape
Version: 0.3.0
Summary: a library traversing django models
Home-page: https://github.com/podhmo/django-mindscape
Author: UNKNOWN
Author-email: UNKNOWN
License: UNKNOWN
Platform: UNKNOWN
Classifier: Programming Language :: Python
Classifier: Programming Language :: Python :: Implementation :: CPython
